{
	"questions": [
		{
			"active": true,
			"pub": ["android","ios","website"],
			"title": "Do you use Wikivoyage and Wikipedia in OsmAnd?",
			"pubdate": "09.08.2021",
			"answers": [
				"No, I don't need guides and articles on the map",
				"Yes, I use guides and articles on the map",
				"I only use Wikipedia articles",
				"I am using these features to improve search in OsmAnd",
				"Other"
			]
		}
	],
	"website_1" : {
		"pubdate" : "09.08.2021",
		"title" : "Do you use Wikivoyage and Wikipedia in OsmAnd?",
		"polldaddyid" : "10890124"
	},
	"website_2" : {
		"pubdate" : "09.08.2021",
		"title" : "Do you use Wikivoyage and Wikipedia in OsmAnd?",
		"polldaddyid" : "10890124"
	},
	"android" : {
		"pubdate" : "09.08.2021",
		"title" : "Do you use Wikivoyage and Wikipedia in OsmAnd?",
		"polldaddyid" : "10890124"
	},
	"ios" : {
		"pubdate" : "09.08.2021",
		"title" : "Do you use Wikivoyage and Wikipedia in OsmAnd?",
		"polldaddyid" : "10890124"
	}
}

